gsd/__init__.py
gsd/__main__.py
gsd/fit.py
gsd/gsd.py
gsd/ref_prob.py
gsd/experimental/__init__.py
gsd/experimental/bootstrap.py
gsd/experimental/fit.py
gsd/experimental/max_entropy.py
ref_gsd-0.2.3.dist-info/METADATA
ref_gsd-0.2.3.dist-info/WHEEL
ref_gsd-0.2.3.dist-info/licenses/LICENSE
ref_gsd-0.2.3.dist-info/RECORD
