Metadata-Version: 2.1
Name: ref_gsd
Version: 0.2.3
Summary: Reference implementation of generalised score distribution in python
Project-URL: Homepage, https://github.com/gsd-authors/gsd
Project-URL: Documentation, https://gsd-authors.github.io/gsd/
Author-email: Krzysztof Rusek <krussek@gmail.com>
License:                                  Apache License
License-File: LICENSE
Keywords: QoE,distribution,jax,test
Classifier: Development Status :: 3 - Alpha
Classifier: Intended Audience :: Developers
Classifier: Intended Audience :: Financial and Insurance Industry
Classifier: Intended Audience :: Information Technology
Classifier: Intended Audience :: Science/Research
Classifier: Intended Audience :: Telecommunications Industry
Classifier: License :: OSI Approved :: Apache Software License
Classifier: Natural Language :: English
Classifier: Programming Language :: Python :: 3
Classifier: Topic :: Scientific/Engineering :: Information Analysis
Classifier: Topic :: Scientific/Engineering :: Mathematics
Requires-Python: >=3.10
Requires-Dist: jax>=0.4.23
Provides-Extra: experimental
Requires-Dist: optimistix>=0.0.6; extra == 'experimental'
